[
  {
    "name": "松茸御飯とやまかけそばSET",
    "price": "【1,680円】",
    "pic": "https://www.takeo-ureshino-cc.jp/wp-content/uploads/2017/01/rest_jan01.jpg"
  },
  {
    "name": "鯖の蒲焼とヒレカツ御前",
    "price": "【1,680円】",
    "pic": "https://www.takeo-ureshino-cc.jp/wp-content/uploads/2017/01/rest_jan02.jpg"
  },
  {
    "name": "豚骨ラーメン",
    "price": "【920円】",
    "pic": "https://www.takeo-ureshino-cc.jp/wp-content/uploads/2017/01/rest_jan03.jpg"
  },
  {
    "name": "有頭エビフライ定食",
    "price": "【1,680円】",
    "pic": "https://www.takeo-ureshino-cc.jp/wp-content/uploads/2017/01/rest_jan04.jpg"
  },
  {
    "name": "タコとトマトの冷製パスタ",
    "price": "【980円】",
    "pic": "https://www.takeo-ureshino-cc.jp/wp-content/uploads/2017/01/rest_jan05.jpg"
  },
  {
    "name": "海鮮爆弾丼",
    "price": "【1,580円】",
    "pic": "https://www.takeo-ureshino-cc.jp/wp-content/uploads/2017/01/rest_jan06.jpg"
  }
]